sql_dhost/__init__.py
sql_dhost/dhost.py
sql_dhost/util/__init__.py
sql_dhost/util/db.py
sql_dhost/util/llms.py
sql_dhost-0.1.1.dist-info/licenses/LICENSE
sql_dhost-0.1.1.dist-info/METADATA
sql_dhost-0.1.1.dist-info/WHEEL
sql_dhost-0.1.1.dist-info/top_level.txt
sql_dhost-0.1.1.dist-info/RECORD
