Metadata-Version: 2.4
Name: sql-dhost
Version: 0.1.1
Summary: A Python package for generating SQL queries using LLMs
Author-email: Sujan Midatani <sujanmidatani7@gmail.com>
Project-URL: Homepage, https://github.com/sujanMidatani7/sql-dhost
Requires-Python: >=3.10
License-File: LICENSE
Requires-Dist: anthropic>=0.50.0
Requires-Dist: openai>=1.77.0
Requires-Dist: psycopg2>=2.9.10
Requires-Dist: python-dotenv>=1.1.0
Requires-Dist: requests>=2.32.3
Dynamic: license-file
